MeineUtils/__init__.py
MeineUtils/General/__init__.py
MeineUtils/General/decorator.py
MeineUtils/General/directory.py
MeineUtils/General/file.py
MeineUtils/General/general.py
MeineUtils/MachineLearning/__init__.py
MeineUtils/MachineLearning/augmentation.py
MeineUtils/MachineLearning/bounding_box.py
MeineUtils/MachineLearning/linear_regression.py
MeineUtils/MachineLearning/logistic_regression.py
MeineUtils/MachineLearning/normalization.py
MeineUtils/MachineLearning/NaturalLanguageProcessing/__init__.py
MeineUtils/MachineLearning/NaturalLanguageProcessing/preprecessing.py
MeineUtils/MachineLearning/NaturalLanguageProcessing/preprocessing.py
MeineUtils/Math/__init__.py
MeineUtils/Math/activation_funciton.py
MeineUtils/Math/general.py
MeineUtils/Math/statistics.py
MeineUtils-0.0.45.dist-info/METADATA
MeineUtils-0.0.45.dist-info/WHEEL
MeineUtils-0.0.45.dist-info/top_level.txt
MeineUtils-0.0.45.dist-info/RECORD
